MANIFEST.in
README.md
embc
setup.py
embc.egg-info/PKG-INFO
embc.egg-info/SOURCES.txt
embc.egg-info/dependency_links.txt
embc.egg-info/top_level.txt
embedded_cmake/__init__.py
embedded_cmake/__main__.py
embedded_cmake/download.py
embedded_cmake/environment.py
embedded_cmake/gitutils.py
embedded_cmake/libs.py
embedded_cmake/templates/README.md
embedded_cmake/templates/Toolchain.cmake
embedded_cmake/templates/library-with-src.cmake
embedded_cmake/templates/library-without-src.cmake