Metadata-Version: 1.1
Name: embc
Version: 0.1.1
Summary: Companion script for embedded cmake
Home-page: http://github.com/MarSik/embc
Author: Martin Sivak
Author-email: mars@montik.net
License: ASL2
Keywords: embedded cmake
Platform: UNKNOWN
Classifier: Development Status :: 3 - Alpha
Classifier: Environment :: Console
Classifier: Intended Audience :: Developers
Classifier: License :: OSI Approved :: Apache Software License
Classifier: Topic :: Software Development :: Build Tools
